notif/__init__.py
notif/fail_decorator.py
notif/notificator.py
notif/version.py
tests/__init__.py
tests/base.py
tests/test_fail_decorator.py
tests/test_notificator.py
notif-0.7.dist-info/LICENSE
notif-0.7.dist-info/METADATA
notif-0.7.dist-info/WHEEL
notif-0.7.dist-info/top_level.txt
notif-0.7.dist-info/RECORD
