Metadata-Version: 2.1
Name: notif
Version: 0.7
Summary: The notification package for every python project
Home-page: https://notificationdoc.ca
Download-URL: https://github.com/davebulaval/notification/archive/v0.7.zip
Author: David Beauchemin
Author-email: david.beauchemin.5@ulaval.ca
License: GPLv3
Classifier: Development Status :: 3 - Alpha
Classifier: Intended Audience :: Developers
Classifier: Intended Audience :: Education
Classifier: Intended Audience :: Science/Research
Classifier: License :: OSI Approved :: GNU General Public License v3 (GPLv3)
Classifier: Programming Language :: Python :: 3
Classifier: Programming Language :: Python :: 3.7
Classifier: Programming Language :: Python :: 3.8
Classifier: Programming Language :: Python :: 3.9
Classifier: Programming Language :: Python :: 3.10
Classifier: Topic :: Software Development :: Libraries
Classifier: Topic :: Software Development :: Libraries :: Python Modules
Requires-Python: >=3.7
License-File: LICENSE
Requires-Dist: requests
Requires-Dist: notify-run
Requires-Dist: pymsteams
